{
  "objects" : [
    {
      "label" : "gomi",
      "x_y_w_h" : [
        437.781,
        323.1166,
        113.8297,
        123.1334
      ]
    },
    {
      "label" : "gomi",
      "x_y_w_h" : [
        394.5763,
        251.3759,
        43.54029,
        67.29446
      ]
    },
    {
      "label" : "gomi",
      "x_y_w_h" : [
        379.375,
        234.2198,
        39.85737,
        47.46225
      ]
    }
  ],
  "image_path" : "\/Users\/quantan\/Downloads\/1\/284.jpg",
  "image_w_h" : [
    640,
    480
  ]
}