{
  "objects" : [
    {
      "label" : "gomi",
      "x_y_w_h" : [
        109.1569,
        246.8163,
        128.167,
        155.3901
      ]
    },
    {
      "label" : "gomi",
      "x_y_w_h" : [
        187.7139,
        232.7643,
        123.3683,
        119.2617
      ]
    },
    {
      "label" : "gomi",
      "x_y_w_h" : [
        318.3683,
        240.0587,
        73.35989,
        110.9773
      ]
    }
  ],
  "image_path" : "\/Users\/quantan\/Downloads\/1\/600.jpg",
  "image_w_h" : [
    640,
    480
  ]
}